dbt/adapters/cratedb/__init__.py
dbt/adapters/cratedb/__version__.py
dbt/adapters/cratedb/column.py
dbt/adapters/cratedb/connections.py
dbt/adapters/cratedb/impl.py
dbt/adapters/cratedb/relation.py
dbt/include/cratedb/__init__.py
dbt/include/cratedb/dbt_project.yml
dbt/include/cratedb/sample_profiles.yml
dbt/include/cratedb/macros/adapters.sql
dbt/include/cratedb/macros/catalog.sql
dbt_cratedb-1.5.3.dist-info/METADATA
dbt_cratedb-1.5.3.dist-info/WHEEL
dbt_cratedb-1.5.3.dist-info/top_level.txt
dbt_cratedb-1.5.3.dist-info/RECORD
