Metadata-Version: 2.1
Name: dbt-cratedb
Version: 1.5.3
Summary: The crate adapter plugin for dbt (data build tool)
Home-page: 
Author: Smartnow
Author-email: julio@smartnow.la
Classifier: Development Status :: 2 - Pre-Alpha
Classifier: License :: OSI Approved :: Apache Software License
Classifier: Operating System :: Microsoft :: Windows
Classifier: Operating System :: MacOS :: MacOS X
Classifier: Operating System :: POSIX :: Linux
Classifier: Programming Language :: Python :: 3.8
Classifier: Programming Language :: Python :: 3.9
Classifier: Programming Language :: Python :: 3.10
Classifier: Programming Language :: Python :: 3.11
Requires-Python: >=3.8.2
Requires-Dist: dbt-core (==1.5.2)
Requires-Dist: crate (==0.32.0)
